bin/paste2file
bin/paste2qrcode
bin/paste2sms
bin/sendsms
bin/wifi2qrcode
desktop/.gitignore
desktop/Makefile
desktop/paste2file.desktop
desktop/paste2file.svg
desktop/paste2file.xcf
desktop/paste2qrcode.desktop
desktop/paste2qrcode.svg
desktop/paste2qrcode.xcf
desktop/paste2sms.desktop
desktop/paste2sms.ico
desktop/paste2sms.svg
desktop/paste2sms.xcf
desktop/png2svg.py
desktop/toto2titi.ico
desktop/toto2titi.svg
desktop/toto2titi.xcf
desktop/wifi2qrcode.desktop
desktop/wifi2qrcode.svg
desktop/wifi2qrcode.xcf
desktop/256x256/paste2file.png
desktop/256x256/paste2qrcode.png
desktop/256x256/paste2sms.png
desktop/256x256/wifi2qrcode.png
desktop/32x32/paste2file.png
desktop/32x32/paste2qrcode.png
desktop/32x32/paste2sms.png
desktop/32x32/wifi2qrcode.png
doc/.gitignore
doc/Makefile
doc/conf.py
doc/faq.rst
doc/index.rst
doc/make.bat
doc/paste2file.rst
doc/paste2qrcode.rst
doc/paste2sms.rst
doc/requirements.txt
doc/wifi2qrcode.rst
doc/_static/screencast.gif
doc/_static/screencast.txt
doc/toto2titi/index.rst
doc/toto2titi/smsprovider.rst
doc/toto2titi/smsprovider/toto2titi.smsprovider.freemobile.rst
paste2file/__init__.py
paste2file/__main__.py
paste2qrcode/__init__.py
paste2qrcode/__main__.py
paste2sms/__init__.py
paste2sms/__main__.py
toto2titi/__init__.py
toto2titi/commandline.py
toto2titi/dialog.py
toto2titi/editor.py
toto2titi/icon.py
toto2titi/imageviewer.py
toto2titi/message.py
toto2titi/selector.py
toto2titi/tkcommon.py
toto2titi/wifi.py
toto2titi/sendsms/__init__.py
toto2titi/sendsms/__main__.py
toto2titi/sendsms/provider/freemobile.py
toto2titi-2.3.0.data/data/share/applications/paste2file.desktop
toto2titi-2.3.0.data/data/share/applications/paste2qrcode.desktop
toto2titi-2.3.0.data/data/share/applications/paste2sms.desktop
toto2titi-2.3.0.data/data/share/applications/wifi2qrcode.desktop
toto2titi-2.3.0.data/data/share/icons/hicolor/256x256/apps/paste2file.png
toto2titi-2.3.0.data/data/share/icons/hicolor/256x256/apps/paste2qrcode.png
toto2titi-2.3.0.dist-info/AUTHORS
toto2titi-2.3.0.dist-info/LICENSE
toto2titi-2.3.0.dist-info/METADATA
toto2titi-2.3.0.dist-info/WHEEL
toto2titi-2.3.0.dist-info/entry_points.txt
toto2titi-2.3.0.dist-info/top_level.txt
toto2titi-2.3.0.dist-info/RECORD
