Metadata-Version: 2.1
Name: toto2titi
Version: 2.3.0
Summary: A rag-bag of small desktop utilities
Home-page: http://framagit.org/spalax/paste2sms
Author: Louis Paternault
Author-email: spalax@gresille.org
License: GPLv3 or any later version
Project-URL: Documentation, http://paste2sms.readthedocs.io
Project-URL: Source, https://framagit.org/spalax/paste2sms
Project-URL: Tracker, https://framagit.org/spalax/paste2sms/issues
Keywords: clipboard sms qrcode wifi paste
Classifier: Development Status :: 5 - Production/Stable
Classifier: Environment :: X11 Applications
Classifier: Intended Audience :: End Users/Desktop
Classifier: License :: OSI Approved :: GNU General Public License v3 or later (GPLv3+)
Classifier: Programming Language :: Python :: 3 :: Only
Classifier: Programming Language :: Python :: 3.8
Classifier: Programming Language :: Python :: 3.9
Classifier: Programming Language :: Python :: 3.10
Classifier: Programming Language :: Python :: 3.11
Classifier: Programming Language :: Python :: 3.12
Classifier: Programming Language :: Python :: 3.13
Classifier: Topic :: Communications :: Telephony
Requires-Python: <4,>=3.8
License-File: LICENSE
License-File: AUTHORS
Requires-Dist: dbus-python
Requires-Dist: notify-py
Requires-Dist: pillow
Requires-Dist: pyperclip
Requires-Dist: pyxdg
Requires-Dist: qrcode
Requires-Dist: requests
